{
  "video_id": "7489203954614553902",
  "video_url": "https://www.tiktok.com/@cbschicago/video/7489203954614553902",
  "publish_date": "4-4",
  "comment_groups": [
    {
      "user": "////////",
      "comments": [
        "он просто спекулирует на рынках , чтобы закупаться на низах. За это сажают"
      ],
      "language": "Other",
      "pure_emoji": false
    },
    {
      "user": "AlexAndrov.🏈",
      "comments": [
        "Только приехал 🤣 Всё по прежнему.. Как и людей в магазинах",
        "6 раз или 6 компаний из 800+ ?🤣"
      ],
      "language": "Other",
      "pure_emoji": false
    },
    {
      "user": "Anatolij Filipov375",
      "comments": [
        "Трамп ещё себя покажет,какой он президент...вы даже не представляете,какая Америка великая держава,она правит всем миром,как скажет,так и будет..."
      ],
      "language": "Other",
      "pure_emoji": false
    },
    {
      "user": "Andrew",
      "comments": [
        "Вывод покупайте EURO ну его с этим долларом"
      ],
      "language": "English",
      "pure_emoji": false
    },
    {
      "user": "Arti",
      "comments": [
        "Это цитата трампа"
      ],
      "language": "Other",
      "pure_emoji": false
    },
    {
      "user": "Asker 24/7",
      "comments": [
        "нас больше интересует почему ты дома в очках а на улице без них"
      ],
      "language": "Other",
      "pure_emoji": false
    },
    {
      "user": "Australia 🇦🇺 imperor",
      "comments": [
        "Спасибо Трампу, Купил акции по дешёвке."
      ],
      "language": "Other",
      "pure_emoji": false
    },
    {
      "user": "Bandera",
      "comments": [
        "Это спецом было сделано, акции упали, он через третьих особ скупил акции, потом отменил указ, акции выросли - продал акции с наценкой. Бизнес (лохотрон) с использованием своих полномочий - махинации."
      ],
      "language": "Other",
      "pure_emoji": false
    },
    {
      "user": "Boba",
      "comments": [
        "Трамп как тот кто симпатизирует «русскому миру» делает все, о чем всегда мечтал «русский мир» – чтобы Америка настало хана"
      ],
      "language": "Other",
      "pure_emoji": false
    },
    {
      "user": "Callder",
      "comments": [
        "Хотя бы он лучше Байдена"
      ],
      "language": "Other",
      "pure_emoji": false
    },
    {
      "user": "Dima Dumitru",
      "comments": [
        "КГБ сила😆"
      ],
      "language": "Other",
      "pure_emoji": false
    },
    {
      "user": "Enquiro",
      "comments": [
        "понял, что все смотрят на него как на клоуна, и решил отступить"
      ],
      "language": "Other",
      "pure_emoji": false
    },
    {
      "user": "Fantasy",
      "comments": [
        "трамп: угадай че выкину"
      ],
      "language": "Other",
      "pure_emoji": false
    },
    {
      "user": "Gans",
      "comments": [
        "тромп барыга-лузер."
      ],
      "language": "Other",
      "pure_emoji": false
    },
    {
      "user": "Ghiță Rolya",
      "comments": [
        "Это уже поздно прецедент уже запущен все будет искать альтернативу😁💪"
      ],
      "language": "Other",
      "pure_emoji": false
    },
    {
      "user": "Innexx1",
      "comments": [
        "A možet zapisal😂"
      ],
      "language": "English",
      "pure_emoji": false
    },
    {
      "user": "Ira Fireal",
      "comments": [
        "Обычная рыночная манипуляция, абсолютно нелегальная. Его подхалуи сегодня заработали миллиарды, скупив все по дешевке. За это они должны быть в тюрьме, но они в администрации США🤗"
      ],
      "language": "Other",
      "pure_emoji": false
    },
    {
      "user": "Irina Amina",
      "comments": [
        "«Трамп не дает сходить в магазин» 😂😂😂"
      ],
      "language": "Other",
      "pure_emoji": false
    },
    {
      "user": "JIOKEH",
      "comments": [
        "Это тактика росии. Принимать скандальные законы, потом их откладывать, чтоб шумиха спала, а потом они вступают в силу уже без публичного объявления 😏"
      ],
      "language": "Other",
      "pure_emoji": false
    },
    {
      "user": "Julia_view",
      "comments": [
        "Все он понимает. Это жесткая манипуляция сток маркетом, которая удвоит, а то и утроит состояние его окружения. Обычное мошенничество, просто супер высокого уровня, в особо крупных размерах,так сказать"
      ],
      "language": "Other",
      "pure_emoji": false
    },
    {
      "user": "Julie in Germany 🇩🇪",
      "comments": [
        "Потому-то ответка от Европы 🔥😄 мы тоже подняли тарифы 😄😄😄"
      ],
      "language": "Other",
      "pure_emoji": false
    },
    {
      "user": "KyPuTe_I7JlaH",
      "comments": [
        "Вспомните мой комментарий ещё.Трамп и та игра с экономикой которая идёт сейчас,укрепит её в 100 раз. Вот увидите Буквально через 3-4 месяца."
      ],
      "language": "Other",
      "pure_emoji": false
    },
    {
      "user": "Limbo",
      "comments": [
        "Я говорил подождите неделю) Сегодня отсрочил а завтра скажет что это я не помню)"
      ],
      "language": "Other",
      "pure_emoji": false
    },
    {
      "user": "MechanicUA",
      "comments": [
        "Для закупа"
      ],
      "language": "Other",
      "pure_emoji": false
    },
    {
      "user": "Meloman",
      "comments": [
        "Трамп это генератор случайных идей"
      ],
      "language": "Other",
      "pure_emoji": false
    },
    {
      "user": "Michelle22",
      "comments": [
        "Трамп підняв тарифи, акції упали, він накупляв дешевих, а потім поставив на паузу, акції підскочили , Трамп їх продав і трошки заробив. Остап Бендер."
      ],
      "language": "Other",
      "pure_emoji": false
    },
    {
      "user": "Mr. UA",
      "comments": [
        "Та він кгбешнік. Все він спецом це робить"
      ],
      "language": "Other",
      "pure_emoji": false
    },
    {
      "user": "Naduxa Ctelmashenko",
      "comments": [
        "В Україні зараз євро дорожче долара,хоча у нас війна"
      ],
      "language": "Other",
      "pure_emoji": false
    },
    {
      "user": "Nika*",
      "comments": [
        "может все таки народ заставит его пройти освидетельствование на приеме врачебной комиссии?"
      ],
      "language": "Other",
      "pure_emoji": false
    },
    {
      "user": "NoName0005",
      "comments": [
        "в Україні вже всі обмінюють долари на євро😁"
      ],
      "language": "Other",
      "pure_emoji": false
    },
    {
      "user": "OBBau",
      "comments": [
        "Путин тоже реально думает что помогает украинскому народу избавиться от нацизма, а сам по факту таким и является"
      ],
      "language": "Other",
      "pure_emoji": false
    },
    {
      "user": "PAPADOS8911",
      "comments": [
        "good good be happy"
      ],
      "language": "English",
      "pure_emoji": false
    },
    {
      "user": "POLITONE",
      "comments": [
        "Трамп агент 😂"
      ],
      "language": "Other",
      "pure_emoji": false
    },
    {
      "user": "Pofer",
      "comments": [
        "через 90 дней он даже не вспомнит об этих тарифах"
      ],
      "language": "Other",
      "pure_emoji": false
    },
    {
      "user": "Ryu Hayabusa",
      "comments": [
        "евро всегда был дороже"
      ],
      "language": "Other",
      "pure_emoji": false
    },
    {
      "user": "Samira Huseynova518",
      "comments": [
        "Трамп очень хорошо понимает что делает!!!!"
      ],
      "language": "Other",
      "pure_emoji": false
    },
    {
      "user": "Sargas",
      "comments": [
        "Я уже боюсь твои новости смотреть )"
      ],
      "language": "Other",
      "pure_emoji": false
    },
    {
      "user": "Sergey Haizenberg😎",
      "comments": [
        "Доиграется трамп"
      ],
      "language": "Other",
      "pure_emoji": false
    },
    {
      "user": "Spotify⚛",
      "comments": [
        "Много ходовка Минус рынка ценны упали купли пошлины отменили ценны взлетели продали"
      ],
      "language": "Other",
      "pure_emoji": false
    },
    {
      "user": "VV",
      "comments": [
        "😂"
      ],
      "language": "Other",
      "pure_emoji": true
    },
    {
      "user": "Wilhelm",
      "comments": [
        "Белый дом опроверг слухи о возможности отложения пошлин. В администрации США назвали неправдой информацию о возможности отложить введение пошлин на 90 дней в контексте торговых переговоро"
      ],
      "language": "Other",
      "pure_emoji": false
    },
    {
      "user": "XV",
      "comments": [
        "Это просто манипуляция на рынках инвестиций и ценных бумаг. Если знать что трамп скажет в очередной раз можно точно знать движение катировок и заработать на этом миллиарды."
      ],
      "language": "Other",
      "pure_emoji": false
    },
    {
      "user": "Yohan Segway",
      "comments": [
        "это не Зеленский. ничего не будет. Собаки дают, караван идёт."
      ],
      "language": "Other",
      "pure_emoji": false
    },
    {
      "user": "anj",
      "comments": [
        "в мене тільки 1 питання - як американський нарід міг вибрати цього 🍊 невігласа ? Як ?😡"
      ],
      "language": "Other",
      "pure_emoji": false
    },
    {
      "user": "blackharbor",
      "comments": [
        "я не удивлюсь, что Трамп был 6 раз банкрот"
      ],
      "language": "Other",
      "pure_emoji": false
    },
    {
      "user": "ertuhhfnjvxvn",
      "comments": [
        "точно😁"
      ],
      "language": "Other",
      "pure_emoji": false
    },
    {
      "user": "gim_us7",
      "comments": [
        "Если что, перед тем как говорить про то что он разрушает экономику сша - ознакомьтесь с его планом"
      ],
      "language": "Other",
      "pure_emoji": false
    },
    {
      "user": "ivanHuțanu5",
      "comments": [
        "только евро💪💪💪👌👌👌👍👍👍"
      ],
      "language": "Other",
      "pure_emoji": false
    },
    {
      "user": "karabas",
      "comments": [
        "против всего мира? 🤣 с помощью с. кореи и Ирана не может одну Украину одолеть.. иди проспись"
      ],
      "language": "Other",
      "pure_emoji": false
    },
    {
      "user": "katalinamil                 💭",
      "comments": [
        "когда он говорил зеленскому про карты скорее всего имел в виду себя, такое ощущение что они играют в покер"
      ],
      "language": "Other",
      "pure_emoji": false
    },
    {
      "user": "keushsvetlanka",
      "comments": [
        "Мене цікавлять настрої його виборців...ось це все норм ??!"
      ],
      "language": "Other",
      "pure_emoji": false
    },
    {
      "user": "madeonly4u",
      "comments": [
        "Дональд сдался сразу как Япония и Китай стали продавать американские долговые облигации, даже 1 день не простоял"
      ],
      "language": "Other",
      "pure_emoji": false
    },
    {
      "user": "maksvorobyov639",
      "comments": [
        "тебе уже нужно звонить в пиар отдел Дональда Трампа пусть оплачивают твои ролики😁😁😁"
      ],
      "language": "Other",
      "pure_emoji": false
    },
    {
      "user": "marino4ka2309",
      "comments": [
        "Пока сходите за покупками,там все поменяется 😂"
      ],
      "language": "Other",
      "pure_emoji": false
    },
    {
      "user": "marmar Kantri",
      "comments": [
        "он подыграл своим акции упали дал скупить и вся игра"
      ],
      "language": "Other",
      "pure_emoji": false
    },
    {
      "user": "mbbob😎",
      "comments": [
        "Это ты не понимаешь что ты говоришь, Трамп гениальный человек"
      ],
      "language": "Other",
      "pure_emoji": false
    },
    {
      "user": "pelletov",
      "comments": [
        "Ждём ответку от Китая плюс ещё 50 ставлю как это любят США один доллар"
      ],
      "language": "Other",
      "pure_emoji": false
    },
    {
      "user": "rendich⁴²",
      "comments": [
        "а кто 9 месяцев назад говорил что США подчиняется весь мир? Виталь, успокойся)"
      ],
      "language": "Other",
      "pure_emoji": false
    },
    {
      "user": "sila",
      "comments": [
        "вывод США слабое государство что по делать против всего мира мржет воевать только Россия"
      ],
      "language": "Other",
      "pure_emoji": false
    },
    {
      "user": "slavagysak",
      "comments": [
        "Трамп пустий як балон газовий."
      ],
      "language": "Other",
      "pure_emoji": false
    },
    {
      "user": "tarchic",
      "comments": [
        "мы устали побеждать!!!"
      ],
      "language": "Other",
      "pure_emoji": false
    },
    {
      "user": "terra",
      "comments": [
        "кто то неплохо заработал на падении акций"
      ],
      "language": "Other",
      "pure_emoji": false
    },
    {
      "user": "user4052829141239",
      "comments": [
        "Трамп действует по плану другана путина"
      ],
      "language": "Other",
      "pure_emoji": false
    },
    {
      "user": "user5084299015446",
      "comments": [
        "трамп плохой президент"
      ],
      "language": "Other",
      "pure_emoji": false
    },
    {
      "user": "user6199584144541",
      "comments": [
        "Возможно китайский юань станет мировой резервной валютой, если рухнет доллар"
      ],
      "language": "Other",
      "pure_emoji": false
    },
    {
      "user": "user7457606179449",
      "comments": [
        "В этой ситуации все потеряют ведь экономика США тесно связана с Китаем"
      ],
      "language": "Other",
      "pure_emoji": false
    },
    {
      "user": "uzer",
      "comments": [
        "Я скажу может и банальность,но есть такая поговорка:\"Если ты плюнешь в ОБЩЕСТВО,оно утрётся,но если ОБЩЕСТВО плюнет в тебя,ты УТОНЕШЬ\".Мораль,хочешь поднять экономику,не будь \"Звездочётом\","
      ],
      "language": "Other",
      "pure_emoji": false
    },
    {
      "user": "vitalya170990",
      "comments": [
        "таке враження що Путін руками трампа мстить всьому світу"
      ],
      "language": "Other",
      "pure_emoji": false
    },
    {
      "user": "walliX",
      "comments": [
        "тупым обманом себе и своей стране можно репутацию конкретно подпортить, потом это на многие годы аукнется и скупление акции не возместят весь ущерб"
      ],
      "language": "Other",
      "pure_emoji": false
    },
    {
      "user": "yuraarhipenko",
      "comments": [
        "трамп слідить за тобой шоб ти не розслаблявся😂"
      ],
      "language": "Other",
      "pure_emoji": false
    },
    {
      "user": "Альона",
      "comments": [
        "ещё один дед маразматик укрепляет,а другой возвращает"
      ],
      "language": "Other",
      "pure_emoji": false
    },
    {
      "user": "Андрей",
      "comments": [
        "Я думаю он преднамеренно разваливает экономику США по заданию путлера 🥺"
      ],
      "language": "Other",
      "pure_emoji": false
    },
    {
      "user": "Бармалей",
      "comments": [
        "Сдался? 😂😂😂 Его \"друзья\" скупили дешёвые акции, которые теперь пойдут вгору.",
        "По сути да."
      ],
      "language": "Other",
      "pure_emoji": false
    },
    {
      "user": "Валерий Новиков670",
      "comments": [
        "Теперь знаю, что такое дименсия."
      ],
      "language": "Other",
      "pure_emoji": false
    },
    {
      "user": "Вася ф4",
      "comments": [
        "Трамп роняет запад эго фейс научил походу)))"
      ],
      "language": "Other",
      "pure_emoji": false
    },
    {
      "user": "Виктор Фёдорович",
      "comments": [
        "А прикинь тебе реально Трамп дивиться 😅👌"
      ],
      "language": "Other",
      "pure_emoji": false
    },
    {
      "user": "Влад",
      "comments": [
        "а как же сенат ??(( то бишь сенат не должен одобрять либо отклонять ??????((?(??"
      ],
      "language": "Other",
      "pure_emoji": false
    },
    {
      "user": "Володимир Кирилюк",
      "comments": [
        "почне кричати що він геній бо зняв тарифи🤣"
      ],
      "language": "Other",
      "pure_emoji": false
    },
    {
      "user": "Віталій Крушний",
      "comments": [
        "🤔🤔🤔🤔🤔Как можно проголосовать за человека который был 6 раз банкротом 🤣🤣🤣🤣🤣🤣🤣🤣🤣🤣🤣"
      ],
      "language": "Other",
      "pure_emoji": false
    },
    {
      "user": "Годжо",
      "comments": [
        "заканчивать войну ❎ поднимать тарифы✅"
      ],
      "language": "Other",
      "pure_emoji": false
    },
    {
      "user": "Димон",
      "comments": [
        "Если опять не передумает...🤕"
      ],
      "language": "Other",
      "pure_emoji": false
    },
    {
      "user": "Жан",
      "comments": [
        "Импичмент трампу"
      ],
      "language": "Other",
      "pure_emoji": false
    },
    {
      "user": "Михайло Боднар",
      "comments": [
        "Дивно як він міг стати президентом"
      ],
      "language": "Other",
      "pure_emoji": false
    },
    {
      "user": "Мотти (котек)",
      "comments": [
        "\"не даёт в соседний магазин съездить\" представляю как он по пятам за ним ходит. И даже сейчас он стоит за машиной и эго спину своим взглядом сверлит\")"
      ],
      "language": "Other",
      "pure_emoji": false
    },
    {
      "user": "ОЛЕГ_UA",
      "comments": [
        "все він розуміє, це людина пуйла, - інакшого пояснення його дій нема"
      ],
      "language": "Other",
      "pure_emoji": false
    },
    {
      "user": "Оля",
      "comments": [
        "Они)))"
      ],
      "language": "Other",
      "pure_emoji": false
    },
    {
      "user": "Просто я",
      "comments": [
        "ХАХАХ реально"
      ],
      "language": "Other",
      "pure_emoji": false
    },
    {
      "user": "Саша",
      "comments": [
        "хочу, чтобы Китай держал свои тарифы, только так американцы поскорее объявят импичмент трампу"
      ],
      "language": "Other",
      "pure_emoji": false
    },
    {
      "user": "Серж",
      "comments": [
        "Трамп этими действиями качает фондовые рынки и зарабатывает миллиарды …. А мы только и умеем блаблаблабла"
      ],
      "language": "Other",
      "pure_emoji": false
    },
    {
      "user": "ФРАНГЛЕНД",
      "comments": [
        "Я не успеваю посмотреть твое видео как выходит новое."
      ],
      "language": "Other",
      "pure_emoji": false
    },
    {
      "user": "Элеонора 🟢",
      "comments": [
        "просто заработали на панике"
      ],
      "language": "Other",
      "pure_emoji": false
    },
    {
      "user": "волонтер - капелан",
      "comments": [
        "🤣🤣🤣🤣🤣 ну ти молодець"
      ],
      "language": "Other",
      "pure_emoji": false
    },
    {
      "user": "гинеколог.",
      "comments": [
        "Так вся сила США это в $, это всем известно, ну и в технологиях, но давайте серьезно на сегодняшний день Китай делает более крутые вещи, чем США, в техническом плане."
      ],
      "language": "Other",
      "pure_emoji": false
    },
    {
      "user": "лисичка",
      "comments": [
        "ошибаетесь. на таких качелях млрдники приближенные к Трампу зарабатывают лярды",
        "уже пошли. заработали на качелях."
      ],
      "language": "Other",
      "pure_emoji": false
    },
    {
      "user": "это база",
      "comments": [
        "только сейчас понял?"
      ],
      "language": "Other",
      "pure_emoji": false
    },
    {
      "user": "░L░E░G░E░N░D░",
      "comments": [
        "У него крыша съехала"
      ],
      "language": "Other",
      "pure_emoji": false
    },
    {
      "user": "✨️Larisa✨️",
      "comments": [
        "трамп у Бога в кредит взял 90 дней...."
      ],
      "language": "Other",
      "pure_emoji": false
    },
    {
      "user": "𝓖𝓻𝓪𝓯_𝓓𝓮𝓵𝓪_𝓒𝓻𝓾𝓪",
      "comments": [
        "Уже просел доллар в соотношении евро и фунта брит."
      ],
      "language": "Other",
      "pure_emoji": false
    }
  ]
}